Metadata-Version: 2.1
Name: core-research
Version: 0.2
Summary: Research CORE ERM - research info module
Home-page: https://github.com/research-core/core-research
Author: Ricardo Ribeiro, Hugo Cachitas
Author-email: ricardojvr@gmail.com, hugo.cachitas@research.fchampalimaud.org
License: MIT
Platform: UNKNOWN
